mseep_mcp_server_filesystem-0.1.3.dist-info/licenses/LICENSE
src/__init__.py
src/log_utils.py
src/main.py
src/server.py
src/file_tools/__init__.py
src/file_tools/directory_utils.py
src/file_tools/edit_file.py
src/file_tools/file_operations.py
src/file_tools/path_utils.py
tests/__init__.py
tests/conftest.py
tests/test_log_utils.py
tests/test_server.py
tests/file_tools/__init__.py
tests/file_tools/test_directory_utils.py
tests/file_tools/test_edit_file.py
tests/file_tools/test_edit_file_api.py
tests/file_tools/test_edit_file_issues.py
tests/file_tools/test_file_operations.py
tests/file_tools/test_markdown_indentation.py
tests/file_tools/test_path_utils.py
mseep_mcp_server_filesystem-0.1.3.dist-info/METADATA
mseep_mcp_server_filesystem-0.1.3.dist-info/WHEEL
mseep_mcp_server_filesystem-0.1.3.dist-info/top_level.txt
mseep_mcp_server_filesystem-0.1.3.dist-info/RECORD
