Metadata-Version: 2.4
Name: mseep-mcp-server-filesystem
Version: 0.1.3
Summary: A simple Model Context Protocol (MCP) server with file operation tools
Home-page: 
Author: mseep
Author-email: support@skydeck.ai
Maintainer: mseep
Maintainer-email: support@skydeck.ai
Keywords: mseep,mcp,server,filesystem,claude,ai,assistant,file-operations
Classifier: Programming Language :: Python :: 3
Classifier: License :: OSI Approved :: MIT License
Classifier: Operating System :: OS Independent
Requires-Python: >=3.6
License-File: LICENSE
Requires-Dist: pathspec>=0.12.1
Requires-Dist: igittigitt>=2.1.5
Requires-Dist: mcp>=1.3.0
Requires-Dist: mcp[server]>=1.3.0
Requires-Dist: mcp[cli]>=1.3.0
Requires-Dist: structlog>=25.2.0
Requires-Dist: python-json-logger>=3.3.0
Dynamic: author
Dynamic: author-email
Dynamic: classifier
Dynamic: description
Dynamic: description-content-type
Dynamic: keywords
Dynamic: license-file
Dynamic: maintainer
Dynamic: maintainer-email
Dynamic: requires-dist
Dynamic: requires-python
Dynamic: summary
